lsst_sphinx_bootstrap_theme/__init__.py
lsst_sphinx_bootstrap_theme/globaltoc.html
lsst_sphinx_bootstrap_theme/layout.html
lsst_sphinx_bootstrap_theme/localtoc.html
lsst_sphinx_bootstrap_theme/searchbox.html
lsst_sphinx_bootstrap_theme/theme.conf
lsst_sphinx_bootstrap_theme/static/bootstrap-astropy.css
lsst_sphinx_bootstrap_theme/static/copybutton.js
lsst_sphinx_bootstrap_theme/static/lsst_inverted_logo.png
lsst_sphinx_bootstrap_theme/static/lsst_inverted_logo.svg
lsst_sphinx_bootstrap_theme/static/lsst_inverted_logo@2x.png
lsst_sphinx_bootstrap_theme/static/sidebar.js
lsst_sphinx_bootstrap_theme/templates/autosummary/base.rst
lsst_sphinx_bootstrap_theme/templates/autosummary/class.rst
lsst_sphinx_bootstrap_theme/templates/autosummary/module.rst
lsst_sphinx_bootstrap_theme-0.1.0.dist-info/DESCRIPTION.rst
lsst_sphinx_bootstrap_theme-0.1.0.dist-info/METADATA
lsst_sphinx_bootstrap_theme-0.1.0.dist-info/RECORD
lsst_sphinx_bootstrap_theme-0.1.0.dist-info/WHEEL
lsst_sphinx_bootstrap_theme-0.1.0.dist-info/metadata.json
lsst_sphinx_bootstrap_theme-0.1.0.dist-info/top_level.txt
