Metadata-Version: 2.0
Name: lsst-sphinx-bootstrap-theme
Version: 0.1.0
Summary: Sphinx theme for LSST Stack documentation built on Bootstrap and astropy-helpers
Home-page: https://github.com/lsst-sqre/lsst_sphinx_bootstrap_theme
Author: Jonathan Sick
Author-email: jsick@lsst.org
License: BSD
Platform: UNKNOWN
Classifier: Development Status :: 4 - Beta
Classifier: Intended Audience :: Developers
Classifier: Framework :: Sphinx :: Theme
Classifier: License :: OSI Approved :: BSD License
Classifier: Operating System :: OS Independent
Classifier: Programming Language :: Python
Classifier: Programming Language :: Python :: 3
